geostore/Dockerfile
geostore/__init__.py
geostore/api_keys.py
geostore/api_responses.py
geostore/aws_keys.py
geostore/aws_message_attributes.py
geostore/aws_response.py
geostore/boto3_config.py
geostore/bundle.bash
geostore/check.py
geostore/check_files_checksums/__init__.py
geostore/check_files_checksums/task.py
geostore/check_files_checksums/utils.py
geostore/check_stac_metadata/__init__.py
geostore/check_stac_metadata/file/.git
geostore/check_stac_metadata/file/.gitignore
geostore/check_stac_metadata/file/.nojekyll
geostore/check_stac_metadata/file/index.html
geostore/check_stac_metadata/file/v1.0.0/schema.json
geostore/check_stac_metadata/file/v2.0.0/schema.json
geostore/check_stac_metadata/geojson-spec/.git
geostore/check_stac_metadata/geojson-spec/.nojekyll
geostore/check_stac_metadata/geojson-spec/Feature.json
geostore/check_stac_metadata/geojson-spec/FeatureCollection.json
geostore/check_stac_metadata/geojson-spec/GeoJSON.json
geostore/check_stac_metadata/geojson-spec/Geometry.json
geostore/check_stac_metadata/geojson-spec/GeometryCollection.json
geostore/check_stac_metadata/geojson-spec/LineString.json
geostore/check_stac_metadata/geojson-spec/MultiLineString.json
geostore/check_stac_metadata/geojson-spec/MultiPoint.json
geostore/check_stac_metadata/geojson-spec/MultiPolygon.json
geostore/check_stac_metadata/geojson-spec/Point.json
geostore/check_stac_metadata/geojson-spec/Polygon.json
geostore/check_stac_metadata/projection/.git
geostore/check_stac_metadata/projection/.gitignore
geostore/check_stac_metadata/projection/.nojekyll
geostore/check_stac_metadata/projection/index.html
geostore/check_stac_metadata/projection/v1.0.0/schema.json
geostore/check_stac_metadata/stac/.git
geostore/check_stac_metadata/stac/.gitignore
geostore/check_stac_metadata/stac/LICENSE
geostore/check_stac_metadata/stac/README.md
geostore/check_stac_metadata/stac/_config.yml
geostore/check_stac_metadata/stac/v0.0.10/aerial-photo/README.md
geostore-0.1.6.dist-info/entry_points.txt
geostore-0.1.6.dist-info/LICENSE
geostore-0.1.6.dist-info/WHEEL
geostore-0.1.6.dist-info/METADATA
geostore-0.1.6.dist-info/RECORD
