Metadata-Version: 2.1
Name: geostore
Version: 0.1.6
Summary: Central storage, management and access for important geospatial datasets developed by LINZ
Home-page: https://github.com/linz/geostore
License: MIT
Keywords: SpatioTemporal Asset Catalog (STAC),Toitū Te Whenua Land Information New Zealand
Author: Bill M. Nelson
Author-email: bmnelson@linz.govt.nz
Requires-Python: >=3.8,<4.0
Classifier: Development Status :: 4 - Beta
Classifier: Environment :: Console
Classifier: Framework :: AWS CDK
Classifier: Framework :: Pytest
Classifier: Intended Audience :: End Users/Desktop
Classifier: Intended Audience :: Information Technology
Classifier: License :: OSI Approved :: MIT License
Classifier: Natural Language :: English
Classifier: Operating System :: POSIX
Classifier: Programming Language :: Python :: 3
Classifier: Programming Language :: Python :: 3.8
Classifier: Programming Language :: Python :: 3.9
Classifier: Topic :: Communications :: File Sharing
Classifier: Topic :: Scientific/Engineering :: GIS
Classifier: Topic :: Utilities
Classifier: Typing :: Typed
Provides-Extra: cdk
Provides-Extra: check_files_checksums
Provides-Extra: check_stac_metadata
Provides-Extra: content_iterator
Provides-Extra: dataset_versions
Provides-Extra: datasets
Provides-Extra: import_asset_file
Provides-Extra: import_dataset
Provides-Extra: import_metadata_file
Provides-Extra: import_status
Provides-Extra: notify_status_update
Provides-Extra: populate_catalog
Provides-Extra: update_dataset_catalog
Provides-Extra: upload_status
Provides-Extra: validation_summary
Requires-Dist: aws-cdk.aws-dynamodb; extra == "cdk"
Requires-Dist: aws-cdk.aws-ec2; extra == "cdk"
Requires-Dist: aws-cdk.aws-ecr; extra == "cdk"
Requires-Dist: aws-cdk.aws-ecr_assets; extra == "cdk"
Requires-Dist: aws-cdk.aws-ecs; extra == "cdk"
Requires-Dist: aws-cdk.aws-events-targets; extra == "cdk"
Requires-Dist: aws-cdk.aws-events; extra == "cdk"
Requires-Dist: aws-cdk.aws-iam; extra == "cdk"
Requires-Dist: aws-cdk.aws-lambda-event-sources; extra == "cdk"
Requires-Dist: aws-cdk.aws-lambda-python; extra == "cdk"
Requires-Dist: aws-cdk.aws-lambda; extra == "cdk"
Requires-Dist: aws-cdk.aws-s3; extra == "cdk"
Requires-Dist: aws-cdk.aws-sns; extra == "cdk"
Requires-Dist: aws-cdk.aws-stepfunctions; extra == "cdk"
Requires-Dist: aws-cdk.aws-stepfunctions_tasks; extra == "cdk"
Requires-Dist: awscli; extra == "cdk"
Requires-Dist: boto3
Requires-Dist: cattrs; extra == "cdk"
Requires-Dist: jsonschema[format]; extra == "check_stac_metadata" or extra == "content_iterator" or extra == "datasets" or extra == "dataset_versions" or extra == "import_dataset" or extra == "import_status" or extra == "notify_status_update" or extra == "populate_catalog" or extra == "update_dataset_catalog" or extra == "upload_status" or extra == "validation_summary"
Requires-Dist: linz-logger; extra == "check_files_checksums" or extra == "check_stac_metadata" or extra == "content_iterator" or extra == "datasets" or extra == "dataset_versions" or extra == "import_asset_file" or extra == "import_dataset" or extra == "import_metadata_file" or extra == "import_status" or extra == "notify_status_update" or extra == "populate_catalog" or extra == "update_dataset_catalog" or extra == "upload_status" or extra == "validation_summary"
Requires-Dist: multihash; extra == "check_files_checksums"
Requires-Dist: pynamodb; extra == "check_files_checksums" or extra == "check_stac_metadata" or extra == "content_iterator" or extra == "datasets" or extra == "dataset_versions" or extra == "import_dataset" or extra == "import_status" or extra == "notify_status_update" or extra == "update_dataset_catalog" or extra == "upload_status" or extra == "validation_summary"
Requires-Dist: pystac; extra == "datasets" or extra == "populate_catalog"
Requires-Dist: slack-sdk[webhook,models]; extra == "notify_status_update"
Requires-Dist: smart-open[s3]; extra == "import_asset_file" or extra == "import_dataset"
Requires-Dist: strict-rfc3339; extra == "check_stac_metadata"
Requires-Dist: typer
Requires-Dist: ulid-py; extra == "datasets" or extra == "dataset_versions" or extra == "import_dataset" or extra == "update_dataset_catalog"
Project-URL: Repository, https://github.com/linz/geostore
